orbax/export/__init__.py
orbax/export/config.py
orbax/export/config_test.py
orbax/export/conftest.py
orbax/export/constants.py
orbax/export/dtensor_export_test.py
orbax/export/dtensor_initialization_test.py
orbax/export/dtensor_utils.py
orbax/export/dtensor_utils_test.py
orbax/export/export_base.py
orbax/export/export_manager.py
orbax/export/export_manager_obm_test.py
orbax/export/export_manager_test.py
orbax/export/export_testing_utils.py
orbax/export/jax_module.py
orbax/export/jax_module_test.py
orbax/export/obm_configs.py
orbax/export/obm_export.py
orbax/export/obm_export_test.py
orbax/export/oex_orchestration.py
orbax/export/oex_orchestration_test.py
orbax/export/serving_config.py
orbax/export/serving_config_test.py
orbax/export/tensorflow_export.py
orbax/export/tensorflow_export_test.py
orbax/export/typing.py
orbax/export/utils.py
orbax/export/utils_test.py
orbax/export/bfloat16_toolkit/bfloat16.cc
orbax/export/bfloat16_toolkit/bfloat16.h
orbax/export/bfloat16_toolkit/converter_options.proto
orbax/export/bfloat16_toolkit/converter_options_v2.proto
orbax/export/bfloat16_toolkit/function_tree.cc
orbax/export/bfloat16_toolkit/function_tree.h
orbax/export/bfloat16_toolkit/graph_analysis.cc
orbax/export/bfloat16_toolkit/graph_analysis.h
orbax/export/bfloat16_toolkit/optim_utils.cc
orbax/export/bfloat16_toolkit/optim_utils.h
orbax/export/bfloat16_toolkit/utils.cc
orbax/export/bfloat16_toolkit/utils.h
orbax/export/bfloat16_toolkit/python/bfloat16.cc
orbax/export/bfloat16_toolkit/python/bfloat16_test.py
orbax/export/bfloat16_toolkit/python/function_tree.cc
orbax/export/bfloat16_toolkit/python/function_tree_test.py
orbax/export/data_processors/data_processor_base.py
orbax/export/data_processors/tf_data_processor.py
orbax/export/data_processors/tf_data_processor_test.py
orbax/export/examples/__init__.py
orbax/export/examples/flax_mnist_main.py
orbax/export/examples/flax_mnist_main_test.py
orbax/export/examples/periodically_export_main.py
orbax_export-0.0.8.dist-info/licenses/LICENSE
orbax_export-0.0.8.dist-info/WHEEL
orbax_export-0.0.8.dist-info/METADATA
orbax_export-0.0.8.dist-info/RECORD
